deprecated/gen_partial.py
deprecated/generate_data copy.py
deprecated/mh copy.py
deprecated/mh_complicated.py
deprecated/mp_utils copy 2.py
deprecated/mp_utils copy.py
deprecated/mp_utils_before_simplify.py
deprecated/mp_utils_complicated.py
deprecated/mp_utils_complicated_copy_20250826.py
deprecated/mp_utils_with_all_njit.py
deprecated/mp_utils_with_rng_shuffle.py
deprecated/run copy.py
pyjpm/__init__.py
pyjpm/generate_data.py
pyjpm/mh.py
pyjpm/mp_utils.py
pyjpm/run.py
pyjpm/utils.py
pyjpm/viz.py
pyjpm/copies/mh copy.py
pyjpm/copies/mh_copy2_20251109.py
pyjpm/copies/mh_copy_20251109.py
pyjpm/copies/mp_utils copy.py
pyjpm/copies/run_copy_20251109.py
pyjpm/copies/test copy.py
pyjpm/copies/utils copy.py
pyjpm/copies/utils_copy_20251109.py
pyjpm/data/__init__.py
pyjpm/test/gen.py
pyjpm/test/test.py
pyjpm-0.8.8.dist-info/licenses/LICENSE
pympebm_copy/__init__.py
pympebm_copy/generate_data.py
pympebm_copy/mh.py
pympebm_copy/mp_utils.py
pympebm_copy/run.py
pympebm_copy/utils.py
pympebm_copy/viz.py
pympebm_copy/data/__init__.py
pympebm_copy/test/gen.py
pympebm_copy/test/test.py
pympebm_old/__init__.py
pympebm_old/run.py
pympebm_old/algorithms/__init__.py
pympebm_old/algorithms/algorithm.py
pympebm_old/data/__init__.py
pympebm_old/test/gen.py
pympebm_old/test/gen_partial.py
pympebm_old/test/test.py
pympebm_old/utils/__init__.py
pympebm_old/utils/data_processing.py
pympebm_old/utils/fast_kde.py
pympebm_old/utils/generate_data.py
pympebm_old/utils/kmeans.py
pympebm_old/utils/logging_utils.py
pympebm_old/utils/runners.py
pympebm_old/utils/ucl_gmm.py
pympebm_old/utils/visualization.py
pyjpm-0.8.8.dist-info/METADATA
pyjpm-0.8.8.dist-info/WHEEL
pyjpm-0.8.8.dist-info/top_level.txt
pyjpm-0.8.8.dist-info/RECORD
